postgresql_mcp_server3/__init__.py
postgresql_mcp_server3/server.py
postgresql_mcp_server3/resources/db_resources.py
postgresql_mcp_server3/tools/db_tool.py
postgresql_mcp_server3/utils/__init__.py
postgresql_mcp_server3/utils/db_config.py
postgresql_mcp_server3/utils/db_operate.py
postgresql_mcp_server3/utils/db_pool.py
postgresql_mcp_server3/utils/logger_util.py
postgresql_mcp_server3-1.0.9.dist-info/licenses/LICENSE
postgresql_mcp_server3-1.0.9.dist-info/METADATA
postgresql_mcp_server3-1.0.9.dist-info/WHEEL
postgresql_mcp_server3-1.0.9.dist-info/entry_points.txt
postgresql_mcp_server3-1.0.9.dist-info/top_level.txt
postgresql_mcp_server3-1.0.9.dist-info/RECORD
